Workbook

Sheet Cover
B2: DEALDESK CRE UNDERWRITING
B3: Investment Underwriting Model
B5: =Assumptions!C5
B6: =Assumptions!C6
B8: Property Type: | C8: =Assumptions!C7
B9: Project Type: | C9: =Assumptions!C8
B10: Units: | C10: =Assumptions!C9
B11: Building SF: | C11: =Assumptions!C10
B13: KEY METRICS
B14: Purchase Price | C14: =Assumptions!C17
B15: Price Per Unit | C15: =Assumptions!C22
B16: Total Project Cost | C16: =Assumptions!C89
B17: Total Equity | C17: =Assumptions!C91
B18: Year 1 NOI | C18: ='Returns Summary'!B12
B19: Going-In Cap Rate | C19: ='Returns Summary'!B13
B20: Year 1 Cash-on-Cash | C20: ='Returns Summary'!B14
B21: Year 1 DSCR | C21: ='Returns Summary'!B15
B22: Equity Multiple | C22: ='Returns Summary'!B25
B23: Hold Period | C23: =Assumptions!C14
B24: LP IRR | C24: ='Cash Waterfall'!D41
B25: Levered IRR | C25: ='Cash Waterfall'!D30
B26: CONFIDENTIAL
B27: Prepared by DealDesk CRE Underwriting.

Sheet Assumptions
A1: DEALDESK — UNDERWRITING ASSUMPTIONS
A2: All blue values are editable inputs. Change any blue cell to model different scenarios.
B4: 1. PROPERTY INFORMATION
B5: Property Name | C5: Sample Property
B6: Address | C6: 123 Main St, Philadelphia, PA 19103
B7: Property Type | C7: Multifamily
B8: Project Type | C8: Hold
B9: Number of Units | C9: 20
B10: Gross Building Area (SF) | C10: 18000
B11: Lot Size (SF) | C11: 8500
B12: Year Built | C12: 1965
B13: Acquisition Date | C13: 2026-01-01
B14: Hold Period (Years) | C14: 10
B16: 2. ACQUISITION
B17: Purchase Price | C17: 2500000
B18: Transfer Tax Rate — Buyer's Share Only | C18: 0.02139
B19: Transfer Tax Amount | C19: =C17*C18
B20: Closing Costs | C20: 75000
B21: Total Acquisition Cost | C21: =C17+C19+C20
B22: Price Per Unit | C22: =IF(C9>0,C17/C9,0)
B23: Price Per SF | C23: =IF(C10>0,C17/C10,0)
B25: 3. SOURCES & USES
B26: Enter $0 for items not applicable.
B28: USES — Acquisition
B29: Purchase Price | C29: =C17
B30: Transfer Tax | C30: =C19
B31: Tenant Buyout | C31: 0
B33: USES — Professional & Due Diligence
B34: Legal — Closing & Borrowing | C34: 25000
B35: Title Insurance | C35: 8000
B36: Legal — Bank | C36: 5000
B37: Appraisal | C37: 5000
B38: Environmental (Phase I/II) | C38: 6000
B39: Architect | C39: 0
B40: Structural Engineer | C40: 0
B41: GeoTech | C41: 0
B42: Surveyor | C42: 3500
B43: Civil Engineer | C43: 0
B44: MEPs | C44: 0
B45: Legal — Zoning | C45: 0
B47: USES — Financing Costs
B48: Acquisition Fee | C48: 25000
B49: Mortgage Interest (Carry) | C49: 0
B50: Mortgage Fees / Origination | C50: =C71*C75
B51: Mezzanine Interest | C51: 0
B53: USES — Soft Costs
B54: Working Capital | C54: 15000
B55: Marketing | C55: 5000
B56: Real Estate Tax (Carry) | C56: 0
B57: Property / BR / Contractor Ins. | C57: 0
B58: Development Fee | C58: 0
B59: Development Equity Pref Return | C59: 0
B60: Permits / Expediting | C60: 0
B62: USES — Hard Costs
B63: Stormwater Management System | C63: 0
B64: Demolition & Site Work | C64: 0
B65: Construction — Hard Costs | C65: 0
B66: Construction — Reserve | C66: 0
B67: GC Profit & Overhead | C67: 0
B69: 4. INITIAL FINANCING
B70: Loan-to-Value (LTV) | C70: 0.7
B71: Initial Loan Amount | C71: =C17*C70
B72: Interest Rate | C72: 0.065
B73: Amortization (Years) | C73: 30
B74: Loan Term (Years) | C74: 10
B75: Origination Fee (%) | C75: 0.01
B76: Origination Fee ($) | C76: =C71*C75
B77: Interest-Only Period (Months) | C77: 0
B78: Monthly Payment (P&I) | C78: =IF(C73>0,PMT(C72/12,C73*12,-C71),C71*C72/12)
B79: Annual Debt Service | C79: =C78*12
B81: SOURCES
B82: Senior Debt | C82: =C71
B83: Mezzanine Debt | C83: 0
B84: GP Equity | C84: 0
B85: LP Equity | C85: 0
B86: Tax Credit Equity | C86: 0
B87: Grants / Subsidies | C87: 0
B89: TOTAL USES | C89: =SUM(C29:C31)+SUM(C34:C45)+SUM(C48:C51)+SUM(C54:C60)+SUM(C63:C67)
B90: TOTAL SOURCES | C90: =SUM(C82:C87)
B91: TOTAL EQUITY REQUIRED | C91: =C89-C82-C83
B92: Surplus / (Gap) | C92: =C90-C89
B94: 5. REFINANCE 1
B95: Refi 1 — Active? (1=Yes, 0=No) | C95: 0 | H95: Set to 1 to activate
B96: Refi 1 — Timing (Year) | C96: 5
B97: Refi 1 — Appraised Value | C97: 3200000
B98: Refi 1 — LTV | C98: 0.7
B99: Refi 1 — New Loan Amount | C99: =C97*C98
B100: Refi 1 — Interest Rate | C100: 0.06
B101: Refi 1 — Amortization (Yrs) | C101: 30
B102: Refi 1 — Loan Term (Yrs) | C102: 10
B103: Refi 1 — Origination Fee (%) | C103: 0.01
B104: Refi 1 — Prepayment Penalty (%) | C104: 0.01
B105: Refi 1 — Closing Costs ($) | C105: 25000
B107: 6. REFINANCE 2
B108: Refi 2 — Active? (1=Yes, 0=No) | C108: 0 | H108: Set to 1 to activate
B109: Refi 2 — Timing (Year) | C109: 8
B110: Refi 2 — Appraised Value | C110: 3800000
B111: Refi 2 — LTV | C111: 0.65
B112: Refi 2 — New Loan Amount | C112: =C110*C111
B113: Refi 2 — Interest Rate | C113: 0.055
...

Sheet Sources & Uses
A1: SOURCES & USES
A2: All values reference Assumptions tab. No hardcoded numbers.
A4: Line Item | B4: Amount | C4: % of Total
A5: Acquisition Costs
A6: Purchase Price | B6: =Assumptions!C17 | C6: =IF(B51<>0,B6/B51,0)
A7: Transfer Tax | B7: =Assumptions!C19 | C7: =IF(B51<>0,B7/B51,0)
A8: Tenant Buyout | B8: =Assumptions!C31 | C8: =IF(B51<>0,B8/B51,0)
A9: Subtotal — Acquisition Costs | B9: =SUM(B6:B8) | C9: =IF(B51<>0,B9/B51,0)
A11: Professional & Due Diligence
A12: Legal — Closing & Borrowing | B12: =Assumptions!C34 | C12: =IF(B51<>0,B12/B51,0)
A13: Title Insurance | B13: =Assumptions!C35 | C13: =IF(B51<>0,B13/B51,0)
A14: Legal — Bank | B14: =Assumptions!C36 | C14: =IF(B51<>0,B14/B51,0)
A15: Appraisal | B15: =Assumptions!C37 | C15: =IF(B51<>0,B15/B51,0)
A16: Environmental (Phase I/II) | B16: =Assumptions!C38 | C16: =IF(B51<>0,B16/B51,0)
A17: Architect | B17: =Assumptions!C39 | C17: =IF(B51<>0,B17/B51,0)
A18: Structural Engineer | B18: =Assumptions!C40 | C18: =IF(B51<>0,B18/B51,0)
A19: GeoTech | B19: =Assumptions!C41 | C19: =IF(B51<>0,B19/B51,0)
A20: Surveyor | B20: =Assumptions!C42 | C20: =IF(B51<>0,B20/B51,0)
A21: Civil Engineer | B21: =Assumptions!C43 | C21: =IF(B51<>0,B21/B51,0)
A22: MEPs | B22: =Assumptions!C44 | C22: =IF(B51<>0,B22/B51,0)
A23: Legal — Zoning | B23: =Assumptions!C45 | C23: =IF(B51<>0,B23/B51,0)
A24: Subtotal — Professional & Due Diligence | B24: =SUM(B12:B23) | C24: =IF(B51<>0,B24/B51,0)
A26: Financing Costs
A27: Acquisition Fee | B27: =Assumptions!C48 | C27: =IF(B51<>0,B27/B51,0)
A28: Mortgage Interest (Carry) | B28: =Assumptions!C49 | C28: =IF(B51<>0,B28/B51,0)
A29: Mortgage Fees / Origination | B29: =Assumptions!C50 | C29: =IF(B51<>0,B29/B51,0)
A30: Mezzanine Interest | B30: =Assumptions!C51 | C30: =IF(B51<>0,B30/B51,0)
A31: Subtotal — Financing Costs | B31: =SUM(B27:B30) | C31: =IF(B51<>0,B31/B51,0)
A33: Soft Costs
A34: Working Capital | B34: =Assumptions!C54 | C34: =IF(B51<>0,B34/B51,0)
A35: Marketing | B35: =Assumptions!C55 | C35: =IF(B51<>0,B35/B51,0)
A36: RE Tax (Carry) | B36: =Assumptions!C56 | C36: =IF(B51<>0,B36/B51,0)
A37: Prop / BR / Contr Insurance | B37: =Assumptions!C57 | C37: =IF(B51<>0,B37/B51,0)
A38: Development Fee | B38: =Assumptions!C58 | C38: =IF(B51<>0,B38/B51,0)
A39: Dev Equity Pref Return | B39: =Assumptions!C59 | C39: =IF(B51<>0,B39/B51,0)
A40: Permits / Expediting | B40: =Assumptions!C60 | C40: =IF(B51<>0,B40/B51,0)
A41: Subtotal — Soft Costs | B41: =SUM(B34:B40) | C41: =IF(B51<>0,B41/B51,0)
A43: Hard Costs
A44: Stormwater Mgmt | B44: =Assumptions!C63 | C44: =IF(B51<>0,B44/B51,0)
A45: Demolition & Site Work | B45: =Assumptions!C64 | C45: =IF(B51<>0,B45/B51,0)
A46: Construction — Hard Costs | B46: =Assumptions!C65 | C46: =IF(B51<>0,B46/B51,0)
A47: Construction — Reserve | B47: =Assumptions!C66 | C47: =IF(B51<>0,B47/B51,0)
A48: GC Profit & Overhead | B48: =Assumptions!C67 | C48: =IF(B51<>0,B48/B51,0)
A49: Subtotal — Hard Costs | B49: =SUM(B44:B48) | C49: =IF(B51<>0,B49/B51,0)
A51: TOTAL USES | B51: =B9+B24+B31+B41+B49
A53: Sources
A54: Senior Debt | B54: =Assumptions!C82
A55: Mezzanine Debt | B55: =Assumptions!C83
A56: GP Equity | B56: =Assumptions!C84
A57: LP Equity | B57: =Assumptions!C85
A58: Tax Credit Equity | B58: =Assumptions!C86
A59: Grants / Subsidies | B59: =Assumptions!C87
A60: TOTAL SOURCES | B60: =SUM(B54:B59)
A62: SURPLUS / (GAP) | B62: =B60-B51

Sheet Constr Interest

Sheet Rent Roll
A1: RENT ROLL
A2: Residential and commercial unit/tenant data. Blue cells are editable inputs.
A4: RESIDENTIAL UNITS
B5: Unit # | C5: Type | D5: SF | E5: Rent/Mo | F5: Rent/SF/Mo | G5: Annual Rent | H5: Status | I5: Lease Exp | J5: Market Rent
B6: 001 | C6: Studio | D6: 450 | E6: 950 | F6: =IF(D6>0,E6/D6,0) | G6: =E6*12 | H6: Occupied | I6: 12/31/2026 | J6: 1000
B7: 002 | C7: Studio | D7: 450 | E7: 950 | F7: =IF(D7>0,E7/D7,0) | G7: =E7*12 | H7: Occupied | I7: 12/31/2026 | J7: 1000
B8: 003 | C8: Studio | D8: 450 | E8: 950 | F8: =IF(D8>0,E8/D8,0) | G8: =E8*12 | H8: Occupied | I8: 12/31/2026 | J8: 1000
B9: 004 | C9: Studio | D9: 450 | E9: 950 | F9: =IF(D9>0,E9/D9,0) | G9: =E9*12 | H9: Occupied | I9: 12/31/2026 | J9: 1000
B10: 005 | C10: Studio | D10: 450 | E10: 950 | F10: =IF(D10>0,E10/D10,0) | G10: =E10*12 | H10: Vacant | I10: 12/31/2026 | J10: 1000
B11: 006 | C11: 1BR | D11: 650 | E11: 1200 | F11: =IF(D11>0,E11/D11,0) | G11: =E11*12 | H11: Occupied | I11: 12/31/2026 | J11: 1275
B12: 007 | C12: 1BR | D12: 650 | E12: 1200 | F12: =IF(D12>0,E12/D12,0) | G12: =E12*12 | H12: Occupied | I12: 12/31/2026 | J12: 1275
B13: 008 | C13: 1BR | D13: 650 | E13: 1200 | F13: =IF(D13>0,E13/D13,0) | G13: =E13*12 | H13: Occupied | I13: 12/31/2026 | J13: 1275
B14: 009 | C14: 1BR | D14: 650 | E14: 1200 | F14: =IF(D14>0,E14/D14,0) | G14: =E14*12 | H14: Occupied | I14: 12/31/2026 | J14: 1275
B15: 010 | C15: 1BR | D15: 650 | E15: 1200 | F15: =IF(D15>0,E15/D15,0) | G15: =E15*12 | H15: Vacant | I15: 12/31/2026 | J15: 1275
B16: 011 | C16: 2BR | D16: 900 | E16: 1500 | F16: =IF(D16>0,E16/D16,0) | G16: =E16*12 | H16: Occupied | I16: 12/31/2026 | J16: 1600
B17: 012 | C17: 2BR | D17: 900 | E17: 1500 | F17: =IF(D17>0,E17/D17,0) | G17: =E17*12 | H17: Occupied | I17: 12/31/2026 | J17: 1600
... B25: 020 | C25: 3BR | D25: 1100 | E25: 1800 | F25: =IF(D25>0,E25/D25,0) | G25: =E25*12 | H25: Vacant | I25: 12/31/2026 | J25: 1900
B27: TOTALS | C27: =COUNTA(C6:C25) | D27: =SUM(D6:D25) | E27: =SUM(E6:E25) | F27: =IF(D27>0,E27/D27,0) | G27: =SUM(G6:G25) | H27: =COUNTIF(H6:H25,"Occupied")&"/"&COUNTA(H6:H25) | J27: =SUM(J6:J25)
B29: Residential GPR (Annual) | E29: =G27
B30: Occupancy Rate | E30: =IF(COUNTA(H6:H25)>0,COUNTIF(H6:H25,"Occupied")/COUNTA(H6:H25),0)
B31: Average Rent/Unit/Mo | E31: =IF(C27>0,E27/C27,0)
A33: COMMERCIAL TENANTS
B34: Tenant | C34: Suite | D34: SF | E34: Rent/SF/Yr | F34: Annual Rent | G34: Lease Type | H34: Start | I34: Expiry | J34: TI/SF
D35: 0 | E35: 0 | F35: =D35*E35 | J35: 0
D36: 0 | E36: 0 | F36: =D36*E36 | J36: 0
D37: 0 | E37: 0 | F37: =D37*E37 | J37: 0
D38: 0 | E38: 0 | F38: =D38*E38 | J38: 0
D39: 0 | E39: 0 | F39: =D39*E39 | J39: 0
B41: TOTALS | D41: =SUM(D35:D39) | E41: =IF(D41>0,F41/D41,0) | F41: =SUM(F35:F39)
B43: Commercial Income (Annual) | E43: =F41
B45: TOTAL GROSS POTENTIAL RENT (Annual) | E45: =E29+E43

Sheet Pro Forma
A1: 10-YEAR PRO FORMA
A2: All Year 1 values reference Assumptions. No hardcoded numbers.
B3: Year 1 | C3: Year 2 | D3: Year 3 | E3: Year 4 | F3: Year 5 | G3: Year 6 | H3: Year 7 | I3: Year 8 | J3: Year 9 | K3: Year 10
A4: Stabilization Factor | B4: =IF(Assumptions!$C$172+Assumptions!$C$181=0,1,((12-MAX(0,MIN(Assumptions!$C$172,12)-MAX(0,0))-MAX(0,MIN(Assumptions!$C$172+Assumptions!$C$181,12)-MAX(Assumptions!$C$172,0)))+MAX(0,MIN(Assumptions!$C$172+Assumptions!$C$181,12)-MAX(Assumptions!$C$172,0))*(1-Assumptions!$C$182))/12) | C4: =IF(Assumptions!$C$172+Assumptions!$C$181=0,1,((12-MAX(0,MIN(Assumptions!$C$172,24)-MAX(0,12))-MAX(0,MIN(Assumptions!$C$172+Assumptions!$C$181,24)-MAX(Assumptions!$C$172,12)))+MAX(0,MIN(Assumptions!$C$172+Assumptions!$C$181,24)-MAX(Assumptions!$C$172,12))*(1-Assumptions!$C$182))/12) | D4: =IF(Assumptions!$C$172+Assumptions!$C$181=0,1,((12-MAX(0,MIN(Assumptions!$C$172,36)-MAX(0,24))-MAX(0,MIN(Assumptions!$C$172+Assumptions!$C$181,36)-MAX(Assumptions!$C$172,24)))+MAX(0,MIN(Assumptions!$C$172+Assumptions!$C$181,36)-MAX(Assumptions!$C$172,24))*(1-Assumptions!$C$182))/12) | E4: =IF(Assumptions!$C$172+Assumptions!$C$181=0,1,((12-MAX(0,MIN(Assumptions!$C$172,48)-MAX(0,36))-MAX(0,MIN(Assumptions!$C$172+Assumptions!$C$181,48)-MAX(Assumptions!$C$172,36)))+MAX(0,MIN(Assumptions!$C$172+Assumptions!$C$181,48)-MAX(Assumptions!$C$172,36))*(1-Assumptions!$C$182))/12) | F4: =IF(Assumptions!$C$172+Assumptions!$C$181=0,1,((12-MAX(0,MIN(Assumptions!$C$172,60)-MAX(0,48))-MAX(0,MIN(Assumptions!$C$172+Assumptions!$C$181,60)-MAX(Assumptions!$C$172,48)))+MAX(0,MIN(Assumptions!$C$172+Assumptions!$C$181,60)-MAX(Assumptions!$C$172,48))*(1-Assumptions!$C$182))/12) | G4: =IF(Assumptions!$C$172+Assumptions!$C$181=0,1,((12-MAX(0,MIN(Assumptions!$C$172,72)-MAX(0,60))-MAX(0,MIN(Assumptions!$C$172+Assumptions!$C$181,72)-MAX(Assumptions!$C$172,60)))+MAX(0,MIN(Assumptions!$C$172+Assumptions!$C$181,72)-MAX(Assumptions!$C$172,60))*(1-Assumptions!$C$182))/12) | H4: =IF(Assumptions!$C$172+Assumptions!$C$181=0,1,((12-MAX(0,MIN(Assumptions!$C$172,84)-MAX(0,72))-MAX(0,MIN(Assumptions!$C$172+Assumptions!$C$181,84)-MAX(Assumptions!$C$172,72)))+MAX(0,MIN(Assumptions!$C$172+Assumptions!$C$181,84)-MAX(Assumptions!$C$172,72))*(1-Assumptions!$C$182))/12) | I4: =IF(Assumptions!$C$172+Assumptions!$C$181=0,1,((12-MAX(0,MIN(Assumptions!$C$172,96)-MAX(0,84))-MAX(0,MIN(Assumptions!$C$172+Assumptions!$C$181,96)-MAX(Assumptions!$C$172,84)))+MAX(0,MIN(Assumptions!$C$172+Assumptions!$C$181,96)-MAX(Assumptions!$C$172,84))*(1-Assumptions!$C$182))/12) | J4: =IF(Assumptions!$C$172+Assumptions!$C$181=0,1,((12-MAX(0,MIN(Assumptions!$C$172,108)-MAX(0,96))-MAX(0,MIN(Assumptions!$C$172+Assumptions!$C$181,108)-MAX(Assumptions!$C$172,96)))+MAX(0,MIN(Assumptions!$C$172+Assumptions!$C$181,108)-MAX(Assumptions!$C$172,96))*(1-Assumptions!$C$182))/12) | K4: =IF(Assumptions!$C$172+Assumptions!$C$181=0,1,((12-MAX(0,MIN(Assumptions!$C$172,120)-MAX(0,108))-MAX(0,MIN(Assumptions!$C$172+Assumptions!$C$181,120)-MAX(Assumptions!$C$172,108)))+MAX(0,MIN(Assumptions!$C$172+Assumptions!$C$181,120)-MAX(Assumptions!$C$172,108))*(1-Assumptions!$C$182))/12)
A5: Income
A6: Gross Potential Rents | B6: ='Rent Roll'!E45 | C6: =B6*(1+Assumptions!$C$135) | D6: =C6*(1+Assumptions!$C$135) | E6: =D6*(1+Assumptions!$C$135) | F6: =E6*(1+Assumptions!$C$135) | G6: =F6*(1+Assumptions!$C$135) | H6: =G6*(1+Assumptions!$C$135) | I6: =H6*(1+Assumptions!$C$135) | J6: =I6*(1+Assumptions!$C$135) | K6: =J6*(1+Assumptions!$C$135)
A7: Loss to Lease | B7: =-B6*Assumptions!$C$137 | C7: =-C6*Assumptions!$C$137 | D7: =-D6*Assumptions!$C$137 | E7: =-E6*Assumptions!$C$137 | F7: =-F6*Assumptions!$C$137 | G7: =-G6*Assumptions!$C$137 | H7: =-H6*Assumptions!$C$137 | I7: =-I6*Assumptions!$C$137 | ... K7: =-K6*Assumptions!$C$137
A8: Total Gross Potential Rent | B8: =B6+B7 | C8: =C6+C7 | D8: =D6+D7 | E8: =E6+E7 | F8: =F6+F7 | G8: =G6+G7 | H8: =H6+H7 | I8: =I6+I7 | ... K8: =K6+K7
A10: CAM Reimbursements | B10: =Assumptions!C138 | C10: =B10*(1+Assumptions!$C$135) | D10: =C10*(1+Assumptions!$C$135) | E10: =D10*(1+Assumptions!$C$135) | F10: =E10*(1+Assumptions!$C$135) | G10: =F10*(1+Assumptions!$C$135) | H10: =G10*(1+Assumptions!$C$135) | I10: =H10*(1+Assumptions!$C$135) | J10: =I10*(1+Assumptions!$C$135) | K10: =J10*(1+Assumptions!$C$135)
A11: Fees (Damages/App/Pet/Late) | B11: =Assumptions!C139 | C11: =B11*(1+Assumptions!$C$135) | D11: =C11*(1+Assumptions!$C$135) | E11: =D11*(1+Assumptions!$C$135) | F11: =E11*(1+Assumptions!$C$135) | G11: =F11*(1+Assumptions!$C$135) | H11: =G11*(1+Assumptions!$C$135) | I11: =H11*(1+Assumptions!$C$135) | J11: =I11*(1+Assumptions!$C$135) | K11: =J11*(1+Assumptions!$C$135)
A12: Total Other Income | B12: =B10+B11 | C12: =C10+C11 | D12: =D10+D11 | E12: =E10+E11 | F12: =F10+F11 | G12: =G10+G11 | H12: =H10+H11 | I12: =I10+I11 | ... K12: =K10+K11
A14: Total Gross Income | B14: =B8+B12 | C14: =C8+C12 | D14: =D8+D12 | E14: =E8+E12 | F14: =F8+F12 | G14: =G8+G12 | H14: =H8+H12 | I14: =I8+I12 | ... K14: =K8+K12
A15: Less: Vacancy & Bad Debt | B15: =-B14*Assumptions!$C$134 | C15: =-C14*Assumptions!$C$134 | D15: =-D14*Assumptions!$C$134 | E15: =-E14*Assumptions!$C$134 | F15: =-F14*Assumptions!$C$134 | G15: =-G14*Assumptions!$C$134 | H15: =-H14*Assumptions!$C$134 | I15: =-I14*Assumptions!$C$134 | ... K15: =-K14*Assumptions!$C$134
A17: Effective Gross Income | B17: =(B14+B15)*B4 | C17: =(C14+C15)*C4 | D17: =(D14+D15)*D4 | E17: =(E14+E15)*E4 | F17: =(F14+F15)*F4 | G17: =(G14+G15)*G4 | H17: =(H14+H15)*H4 | I17: =(I14+I15)*I4 | ... K17: =(K14+K15)*K4
A19: Operating Expenses — Fixed
A20: Real Estate Taxes | B20: =Assumptions!C142 | C20: =B20*(1+Assumptions!$C$136) | D20: =C20*(1+Assumptions!$C$136) | E20: =D20*(1+Assumptions!$C$136) | F20: =E20*(1+Assumptions!$C$136) | G20: =F20*(1+Assumptions!$C$136) | H20: =G20*(1+Assumptions!$C$136) | I20: =H20*(1+Assumptions!$C$136) | J20: =I20*(1+Assumptions!$C$136) | K20: =J20*(1+Assumptions!$C$136)
A21: Insurance | B21: =Assumptions!C143 | C21: =B21*(1+Assumptions!$C$136) | D21: =C21*(1+Assumptions!$C$136) | E21: =D21*(1+Assumptions!$C$136) | F21: =E21*(1+Assumptions!$C$136) | G21: =F21*(1+Assumptions!$C$136) | H21: =G21*(1+Assumptions!$C$136) | I21: =H21*(1+Assumptions!$C$136) | J21: =I21*(1+Assumptions!$C$136) | K21: =J21*(1+Assumptions!$C$136)
A22: Gas | B22: =Assumptions!C144 | C22: =B22*(1+Assumptions!$C$136) | D22: =C22*(1+Assumptions!$C$136) | E22: =D22*(1+Assumptions!$C$136) | F22: =E22*(1+Assumptions!$C$136) | G22: =F22*(1+Assumptions!$C$136) | H22: =G22*(1+Assumptions!$C$136) | I22: =H22*(1+Assumptions!$C$136) | J22: =I22*(1+Assumptions!$C$136) | K22: =J22*(1+Assumptions!$C$136)
A23: Water & Sewer | B23: =Assumptions!C145 | C23: =B23*(1+Assumptions!$C$136) | D23: =C23*(1+Assumptions!$C$136) | E23: =D23*(1+Assumptions!$C$136) | F23: =E23*(1+Assumptions!$C$136) | G23: =F23*(1+Assumptions!$C$136) | H23: =G23*(1+Assumptions!$C$136) | I23: =H23*(1+Assumptions!$C$136) | J23: =I23*(1+Assumptions!$C$136) | K23: =J23*(1+Assumptions!$C$136)
A24: Electric | B24: =Assumptions!C146 | C24: =B24*(1+Assumptions!$C$136) | D24: =C24*(1+Assumptions!$C$136) | E24: =D24*(1+Assumptions!$C$136) | F24: =E24*(1+Assumptions!$C$136) | G24: =F24*(1+Assumptions!$C$136) | H24: =G24*(1+Assumptions!$C$136) | I24: =H24*(1+Assumptions!$C$136) | J24: =I24*(1+Assumptions!$C$136) | K24: =J24*(1+Assumptions!$C$136)
A25: License / Inspections | B25: =Assumptions!C147 | C25: =B25*(1+Assumptions!$C$136) | D25: =C25*(1+Assumptions!$C$136) | E25: =D25*(1+Assumptions!$C$136) | F25: =E25*(1+Assumptions!$C$136) | G25: =F25*(1+Assumptions!$C$136) | H25: =G25*(1+Assumptions!$C$136) | I25: =H25*(1+Assumptions!$C$136) | J25: =I25*(1+Assumptions!$C$136) | K25: =J25*(1+Assumptions!$C$136)
A26: Trash Removal | B26: =Assumptions!C148 | C26: =B26*(1+Assumptions!$C$136) | D26: =C26*(1+Assumptions!$C$136) | E26: =D26*(1+Assumptions!$C$136) | F26: =E26*(1+Assumptions!$C$136) | G26: =F26*(1+Assumptions!$C$136) | H26: =G26*(1+Assumptions!$C$136) | I26: =H26*(1+Assumptions!$C$136) | J26: =I26*(1+Assumptions!$C$136) | K26: =J26*(1+Assumptions!$C$136)
A27: Total Fixed Expenses | B27: =B20+B21+B22+B23+B24+B25+B26 | C27: =C20+C21+C22+C23+C24+C25+C26 | D27: =D20+D21+D22+D23+D24+D25+D26 | E27: =E20+E21+E22+E23+E24+E25+E26 | F27: =F20+F21+F22+F23+F24+F25+F26 | G27: =G20+G21+G22+G23+G24+G25+G26 | H27: =H20+H21+H22+H23+H24+H25+H26 | I27: =I20+I21+I22+I23+I24+I25+I26 | ... K27: =K20+K21+K22+K23+K24+K25+K26
A29: Operating Expenses — Variable
A30: Management Fee | B30: =B17*Assumptions!$C$152 | C30: =C17*Assumptions!$C$152 | D30: =D17*Assumptions!$C$152 | E30: =E17*Assumptions!$C$152 | F30: =F17*Assumptions!$C$152 | G30: =G17*Assumptions!$C$152 | H30: =H17*Assumptions!$C$152 | I30: =I17*Assumptions!$C$152 | ... K30: =K17*Assumptions!$C$152
A31: Salaries | B31: =Assumptions!C153 | C31: =B31*(1+Assumptions!$C$136) | D31: =C31*(1+Assumptions!$C$136) | E31: =D31*(1+Assumptions!$C$136) | F31: =E31*(1+Assumptions!$C$136) | G31: =F31*(1+Assumptions!$C$136) | H31: =G31*(1+Assumptions!$C$136) | I31: =H31*(1+Assumptions!$C$136) | J31: =I31*(1+Assumptions!$C$136) | K31: =J31*(1+Assumptions!$C$136)
A32: Repairs / Maint / Turnover:
A33: Repairs | B33: =Assumptions!C154 | C33: =B33*(1+Assumptions!$C$136) | D33: =C33*(1+Assumptions!$C$136) | E33: =D33*(1+Assumptions!$C$136) | F33: =E33*(1+Assumptions!$C$136) | G33: =F33*(1+Assumptions!$C$136) | H33: =G33*(1+Assumptions!$C$136) | I33: =H33*(1+Assumptions!$C$136) | J33: =I33*(1+Assumptions!$C$136) | K33: =J33*(1+Assumptions!$C$136)
A34: Exterminator | B34: =Assumptions!C155 | C34: =B34*(1+Assumptions!$C$136) | D34: =C34*(1+Assumptions!$C$136) | E34: =D34*(1+Assumptions!$C$136) | F34: =E34*(1+Assumptions!$C$136) | G34: =F34*(1+Assumptions!$C$136) | H34: =G34*(1+Assumptions!$C$136) | I34: =H34*(1+Assumptions!$C$136) | J34: =I34*(1+Assumptions!$C$136) | K34: =J34*(1+Assumptions!$C$136)
A35: Cleaning / Maintenance | B35: =Assumptions!C156 | C35: =B35*(1+Assumptions!$C$136) | D35: =C35*(1+Assumptions!$C$136) | E35: =D35*(1+Assumptions!$C$136) | F35: =E35*(1+Assumptions!$C$136) | G35: =F35*(1+Assumptions!$C$136) | H35: =G35*(1+Assumptions!$C$136) | I35: =H35*(1+Assumptions!$C$136) | J35: =I35*(1+Assumptions!$C$136) | K35: =J35*(1+Assumptions!$C$136)
A36: Turnover | B36: =Assumptions!C157 | C36: =B36*(1+Assumptions!$C$136) | D36: =C36*(1+Assumptions!$C$136) | E36: =D36*(1+Assumptions!$C$136) | F36: =E36*(1+Assumptions!$C$136) | G36: =F36*(1+Assumptions!$C$136) | H36: =G36*(1+Assumptions!$C$136) | I36: =H36*(1+Assumptions!$C$136) | J36: =I36*(1+Assumptions!$C$136) | K36: =J36*(1+Assumptions!$C$136)
A37: Advertising | B37: =Assumptions!C158 | C37: =B37*(1+Assumptions!$C$136) | D37: =C37*(1+Assumptions!$C$136) | E37: =D37*(1+Assumptions!$C$136) | F37: =E37*(1+Assumptions!$C$136) | G37: =F37*(1+Assumptions!$C$136) | H37: =G37*(1+Assumptions!$C$136) | I37: =H37*(1+Assumptions!$C$136) | J37: =I37*(1+Assumptions!$C$136) | K37: =J37*(1+Assumptions!$C$136)
A38: Landscape / Snow | B38: =Assumptions!C159 | C38: =B38*(1+Assumptions!$C$136) | D38: =C38*(1+Assumptions!$C$136) | E38: =D38*(1+Assumptions!$C$136) | F38: =E38*(1+Assumptions!$C$136) | G38: =F38*(1+Assumptions!$C$136) | H38: =G38*(1+Assumptions!$C$136) | I38: =H38*(1+Assumptions!$C$136) | J38: =I38*(1+Assumptions!$C$136) | K38: =J38*(1+Assumptions!$C$136)
A39: Admin / Legal / Acct / Office:
A40: Admin / Legal / Acct. | B40: =Assumptions!C160 | C40: =B40*(1+Assumptions!$C$136) | D40: =C40*(1+Assumptions!$C$136) | E40: =D40*(1+Assumptions!$C$136) | F40: =E40*(1+Assumptions!$C$136) | G40: =F40*(1+Assumptions!$C$136) | H40: =G40*(1+Assumptions!$C$136) | I40: =H40*(1+Assumptions!$C$136) | J40: =I40*(1+Assumptions!$C$136) | K40: =J40*(1+Assumptions!$C$136)
A41: Office / Phone / Supplies | B41: =Assumptions!C161 | C41: =B41*(1+Assumptions!$C$136) | D41: =C41*(1+Assumptions!$C$136) | E41: =D41*(1+Assumptions!$C$136) | F41: =E41*(1+Assumptions!$C$136) | G41: =F41*(1+Assumptions!$C$136) | H41: =G41*(1+Assumptions!$C$136) | I41: =H41*(1+Assumptions!$C$136) | J41: =I41*(1+Assumptions!$C$136) | K41: =J41*(1+Assumptions!$C$136)
A42: Miscellaneous | B42: =Assumptions!C162 | C42: =B42*(1+Assumptions!$C$136) | D42: =C42*(1+Assumptions!$C$136) | E42: =D42*(1+Assumptions!$C$136) | F42: =E42*(1+Assumptions!$C$136) | G42: =F42*(1+Assumptions!$C$136) | H42: =G42*(1+Assumptions!$C$136) | I42: =H42*(1+Assumptions!$C$136) | J42: =I42*(1+Assumptions!$C$136) | K42: =J42*(1+Assumptions!$C$136)
A43: Total Variable Expenses | B43: =B30+B31+B33+B34+B35+B36+B37+B38+B40+B41+B42 | C43: =C30+C31+C33+C34+C35+C36+C37+C38+C40+C41+C42 | D43: =D30+D31+D33+D34+D35+D36+D37+D38+D40+D41+D42 | E43: =E30+E31+E33+E34+E35+E36+E37+E38+E40+E41+E42 | F43: =F30+F31+F33+F34+F35+F36+F37+F38+F40+F41+F42 | G43: =G30+G31+G33+G34+G35+G36+G37+G38+G40+G41+G42 | H43: =H30+H31+H33+H34+H35+H36+H37+H38+H40+H41+H42 | I43: =I30+I31+I33+I34+I35+I36+I37+I38+I40+I41+I42 | ... K43: =K30+K31+K33+K34+K35+K36+K37+K38+K40+K41+K42
A45: Total Expenses | B45: =B27+B43 | C45: =C27+C43 | D45: =D27+D43 | E45: =E27+E43 | F45: =F27+F43 | G45: =G27+G43 | H45: =H27+H43 | I45: =I27+I43 | ... K45: =K27+K43
A46: Revenue / Expense Ratio | B46: =IF(B17>0,B45/B17,0) | C46: =IF(C17>0,C45/C17,0) | D46: =IF(D17>0,D45/D17,0) | E46: =IF(E17>0,E45/E17,0) | F46: =IF(F17>0,F45/F17,0) | G46: =IF(G17>0,G45/G17,0) | H46: =IF(H17>0,H45/H17,0) | I46: =IF(I17>0,I45/I17,0) | ... K46: =IF(K17>0,K45/K17,0)
A47: Expenses per Unit | B47: =IF(Assumptions!$C$9>0,B45/Assumptions!$C$9,0) | C47: =IF(Assumptions!$C$9>0,C45/Assumptions!$C$9,0) | D47: =IF(Assumptions!$C$9>0,D45/Assumptions!$C$9,0) | E47: =IF(Assumptions!$C$9>0,E45/Assumptions!$C$9,0) | F47: =IF(Assumptions!$C$9>0,F45/Assumptions!$C$9,0) | G47: =IF(Assumptions!$C$9>0,G45/Assumptions!$C$9,0) | H47: =IF(Assumptions!$C$9>0,H45/Assumptions!$C$9,0) | I47: =IF(Assumptions!$C$9>0,I45/Assumptions!$C$9,0) | ... K47: =IF(Assumptions!$C$9>0,K45/Assumptions!$C$9,0)
A49: Net Operating Income | B49: =B17-B45 | C49: =C17-C45 | D49: =D17-D45 | E49: =E17-E45 | F49: =F17-F45 | G49: =G17-G45 | H49: =H17-H45 | I49: =I17-I45 | ... K49: =K17-K45
A50: Capitalization Rate | B50: =IF(Assumptions!$C$17>0,B49/Assumptions!$C$17,0) | C50: =IF(Assumptions!$C$17>0,C49/Assumptions!$C$17,0) | D50: =IF(Assumptions!$C$17>0,D49/Assumptions!$C$17,0) | E50: =IF(Assumptions!$C$17>0,E49/Assumptions!$C$17,0) | F50: =IF(Assumptions!$C$17>0,F49/Assumptions!$C$17,0) | G50: =IF(Assumptions!$C$17>0,G49/Assumptions!$C$17,0) | H50: =IF(Assumptions!$C$17>0,H49/Assumptions!$C$17,0) | I50: =IF(Assumptions!$C$17>0,I49/Assumptions!$C$17,0) | ... K50: =IF(Assumptions!$C$17>0,K49/Assumptions!$C$17,0)
A52: Below the Line
A53: Commissions | B53: =Assumptions!C166 | C53: 0 | D53: 0 | E53: 0 | F53: 0 | G53: 0 | H53: 0 | I53: 0 | J53: 0 | K53: 0
A54: Capital Reserves | B54: =Assumptions!$C167*Assumptions!$C9 | C54: =Assumptions!$C$167*Assumptions!$C$9 | D54: =Assumptions!$C$167*Assumptions!$C$9 | E54: =Assumptions!$C$167*Assumptions!$C$9 | F54: =Assumptions!$C$167*Assumptions!$C$9 | G54: =Assumptions!$C$167*Assumptions!$C$9 | H54: =Assumptions!$C$167*Assumptions!$C$9 | I54: =Assumptions!$C$167*Assumptions!$C$9 | J54: =Assumptions!$C$167*Assumptions!$C$9 | K54: =Assumptions!$C$167*Assumptions!$C$9
A55: Renovations | B55: =Assumptions!C168 | C55: 0 | D55: 0 | E55: 0 | F55: 0 | G55: 0 | H55: 0 | I55: 0 | J55: 0 | K55: 0
A57: Net Operating Cash Flow | B57: =B49-B53-B54-B55 | C57: =C49-C53-C54-C55 | D57: =D49-D53-D54-D55 | E57: =E49-E53-E54-E55 | F57: =F49-F53-F54-F55 | G57: =G49-G53-G54-G55 | H57: =H49-H53-H54-H55 | I57: =I49-I53-I54-I55 | ... K57: =K49-K53-K54-K55
A59: Debt Service
A60: Annual Debt Service | B60: =IF(AND(Assumptions!$C95=1,1>=Assumptions!$C96),PMT(Assumptions!$C100/12,Assumptions!$C101*12,-Assumptions!$C99)*12,Assumptions!$C79) | C60: =IF(AND(Assumptions!$C95=1,2>=Assumptions!$C96),PMT(Assumptions!$C100/12,Assumptions!$C101*12,-Assumptions!$C99)*12,Assumptions!$C79) | D60: =IF(AND(Assumptions!$C95=1,3>=Assumptions!$C96),PMT(Assumptions!$C100/12,Assumptions!$C101*12,-Assumptions!$C99)*12,Assumptions!$C79) | E60: =IF(AND(Assumptions!$C95=1,4>=Assumptions!$C96),PMT(Assumptions!$C100/12,Assumptions!$C101*12,-Assumptions!$C99)*12,Assumptions!$C79) | F60: =IF(AND(Assumptions!$C95=1,5>=Assumptions!$C96),PMT(Assumptions!$C100/12,Assumptions!$C101*12,-Assumptions!$C99)*12,Assumptions!$C79) | G60: =IF(AND(Assumptions!$C95=1,6>=Assumptions!$C96),PMT(Assumptions!$C100/12,Assumptions!$C101*12,-Assumptions!$C99)*12,Assumptions!$C79) | H60: =IF(AND(Assumptions!$C95=1,7>=Assumptions!$C96),PMT(Assumptions!$C100/12,Assumptions!$C101*12,-Assumptions!$C99)*12,Assumptions!$C79) | I60: =IF(AND(Assumptions!$C95=1,8>=Assumptions!$C96),PMT(Assumptions!$C100/12,Assumptions!$C101*12,-Assumptions!$C99)*12,Assumptions!$C79) | J60: =IF(AND(Assumptions!$C95=1,9>=Assumptions!$C96),PMT(Assumptions!$C100/12,Assumptions!$C101*12,-Assumptions!$C99)*12,Assumptions!$C79) | K60: =IF(AND(Assumptions!$C95=1,10>=Assumptions!$C96),PMT(Assumptions!$C100/12,Assumptions!$C101*12,-Assumptions!$C99)*12,Assumptions!$C79)
A61: DSCR | B61: =IF(B60>0,B49/B60,0) | C61: =IF(C60>0,C49/C60,0) | D61: =IF(D60>0,D49/D60,0) | E61: =IF(E60>0,E49/E60,0) | F61: =IF(F60>0,F49/F60,0) | G61: =IF(G60>0,G49/G60,0) | H61: =IF(H60>0,H49/H60,0) | I61: =IF(I60>0,I49/I60,0) | ... K61: =IF(K60>0,K49/K60,0)
A63: Free Cash Flow | B63: =B57-B60 | C63: =C57-C60 | D63: =D57-D60 | E63: =E57-E60 | F63: =F57-F60 | G63: =G57-G60 | H63: =H57-H60 | I63: =I57-I60 | ... K63: =K57-K60

Sheet Refi Analysis
A1: REFINANCE ANALYSIS
B3: Refi 1 | C3: Refi 2 | D3: Refi 3
A4: Active? | B4: =Assumptions!C95 | C4: =Assumptions!C108 | D4: =Assumptions!C121
A5: Timing (Year) | B5: =Assumptions!C96 | C5: =Assumptions!C109 | D5: =Assumptions!C122
A6: Appraised Value | B6: =Assumptions!C97 | C6: =Assumptions!C110 | D6: =Assumptions!C123
A7: LTV | B7: =Assumptions!C98 | C7: =Assumptions!C111 | D7: =Assumptions!C124
A8: New Loan Amount | B8: =Assumptions!C99 | C8: =Assumptions!C112 | D8: =Assumptions!C125
A9: Interest Rate | B9: =Assumptions!C100 | C9: =Assumptions!C113 | D9: =Assumptions!C126
A10: Amortization | B10: =Assumptions!C101 | C10: =Assumptions!C114 | D10: =Assumptions!C127
A11: Term | B11: =Assumptions!C102 | C11: =Assumptions!C115 | D11: =Assumptions!C128
A12: Orig Fee (%) | B12: =Assumptions!C103 | C12: =Assumptions!C116 | D12: =Assumptions!C129
A13: Prepay Penalty (%) | B13: =Assumptions!C104 | C13: =Assumptions!C117 | D13: =Assumptions!C130
A14: Closing Costs | B14: =Assumptions!C105 | C14: =Assumptions!C118 | D14: =Assumptions!C131
A16: Calculated Proceeds
A17: Existing Loan Balance | B17: =IF(B4=1,Assumptions!C71,0) | C17: =IF(C4=1,IF(B4=1,B8,Assumptions!C71),0) | D17: =IF(D4=1,IF(C4=1,C8,IF(B4=1,B8,Assumptions!C71)),0)
A18: Prepayment Penalty ($) | B18: =B17*B13 | C18: =C17*C13 | D18: =D17*D13
A19: Origination Fee ($) | B19: =B8*B12 | C19: =C8*C12 | D19: =D8*D12
A20: Total Refi Costs | B20: =B18+B19+B14 | C20: =C18+C19+C14 | D20: =D18+D19+D14
A22: NET REFI PROCEEDS | B22: =IF(B4=1,B8-B17-B20,0) | C22: =IF(C4=1,C8-C17-C20,0) | D22: =IF(D4=1,D8-D17-D20,0)

Sheet Amort - Initial
A1: AMORT - INITIAL
A2: Initial acquisition loan.
A3: Loan Amount | B3: =Assumptions!C71
A4: Annual Rate | B4: =Assumptions!C72
A5: Amort (Years) | B5: =Assumptions!C73
A6: Monthly Payment | B6: =IF(B5>0,PMT(B4/12,B5*12,-B3),0)
A8: Month | B8: Payment | C8: Principal | D8: Interest | E8: Balance
A9: 1 | B9: =$B$6 | C9: =B9-D9 | D9: =$B$3*$B$4/12 | E9: =$B$3-C9
A10: 2 | B10: =$B$6 | C10: =B10-D10 | D10: =E9*$B$4/12 | E10: =E9-C10
A11: 3 | B11: =$B$6 | C11: =B11-D11 | D11: =E10*$B$4/12 | E11: =E10-C11
A12: 4 | B12: =$B$6 | C12: =B12-D12 | D12: =E11*$B$4/12 | E12: =E11-C12
A13: 5 | B13: =$B$6 | C13: =B13-D13 | D13: =E12*$B$4/12 | E13: =E12-C13
A14: 6 | B14: =$B$6 | C14: =B14-D14 | D14: =E13*$B$4/12 | E14: =E13-C14
A15: 7 | B15: =$B$6 | C15: =B15-D15 | D15: =E14*$B$4/12 | E15: =E14-C15
A16: 8 | B16: =$B$6 | C16: =B16-D16 | D16: =E15*$B$4/12 | E16: =E15-C16
A17: 9 | B17: =$B$6 | C17: =B17-D17 | D17: =E16*$B$4/12 | E17: =E16-C17
A18: 10 | B18: =$B$6 | C18: =B18-D18 | D18: =E17*$B$4/12 | E18: =E17-C18
A19: 11 | B19: =$B$6 | C19: =B19-D19 | D19: =E18*$B$4/12 | E19: =E18-C19
A20: 12 | B20: =$B$6 | C20: =B20-D20 | D20: =E19*$B$4/12 | E20: =E19-C20
A21: 13 | B21: =$B$6 | C21: =B21-D21 | D21: =E20*$B$4/12 | E21: =E20-C21
... A368: 360 | B368: =$B$6 | C368: =B368-D368 | D368: =E367*$B$4/12 | E368: =E367-C368

Sheet Amort - Refi 1
A1: AMORT - REFI 1
A2: Blank until Refi 1 activated.
A3: Loan Amount | B3: =Assumptions!C99
A4: Annual Rate | B4: =Assumptions!C100
A5: Amort (Years) | B5: =Assumptions!C101
A6: Monthly Payment | B6: =IF(B5>0,PMT(B4/12,B5*12,-B3),0)
A8: Month | B8: Payment | C8: Principal | D8: Interest | E8: Balance
A9: 1 | B9: =$B$6 | C9: =B9-D9 | D9: =$B$3*$B$4/12 | E9: =$B$3-C9
A10: 2 | B10: =$B$6 | C10: =B10-D10 | D10: =E9*$B$4/12 | E10: =E9-C10
A11: 3 | B11: =$B$6 | C11: =B11-D11 | D11: =E10*$B$4/12 | E11: =E10-C11
A12: 4 | B12: =$B$6 | C12: =B12-D12 | D12: =E11*$B$4/12 | E12: =E11-C12
A13: 5 | B13: =$B$6 | C13: =B13-D13 | D13: =E12*$B$4/12 | E13: =E12-C13
A14: 6 | B14: =$B$6 | C14: =B14-D14 | D14: =E13*$B$4/12 | E14: =E13-C14
A15: 7 | B15: =$B$6 | C15: =B15-D15 | D15: =E14*$B$4/12 | E15: =E14-C15
A16: 8 | B16: =$B$6 | C16: =B16-D16 | D16: =E15*$B$4/12 | E16: =E15-C16
A17: 9 | B17: =$B$6 | C17: =B17-D17 | D17: =E16*$B$4/12 | E17: =E16-C17
A18: 10 | B18: =$B$6 | C18: =B18-D18 | D18: =E17*$B$4/12 | E18: =E17-C18
A19: 11 | B19: =$B$6 | C19: =B19-D19 | D19: =E18*$B$4/12 | E19: =E18-C19
A20: 12 | B20: =$B$6 | C20: =B20-D20 | D20: =E19*$B$4/12 | E20: =E19-C20
A21: 13 | B21: =$B$6 | C21: =B21-D21 | D21: =E20*$B$4/12 | E21: =E20-C21
... A368: 360 | B368: =$B$6 | C368: =B368-D368 | D368: =E367*$B$4/12 | E368: =E367-C368

Sheet Amort - Refi 2
A1: AMORT - REFI 2
A2: Blank until Refi 2 activated.
A3: Loan Amount | B3: =Assumptions!C112
A4: Annual Rate | B4: =Assumptions!C113
A5: Amort (Years) | B5: =Assumptions!C114
A6: Monthly Payment | B6: =IF(B5>0,PMT(B4/12,B5*12,-B3),0)
A8: Month | B8: Payment | C8: Principal | D8: Interest | E8: Balance
A9: 1 | B9: =$B$6 | C9: =B9-D9 | D9: =$B$3*$B$4/12 | E9: =$B$3-C9
A10: 2 | B10: =$B$6 | C10: =B10-D10 | D10: =E9*$B$4/12 | E10: =E9-C10
A11: 3 | B11: =$B$6 | C11: =B11-D11 | D11: =E10*$B$4/12 | E11: =E10-C11
A12: 4 | B12: =$B$6 | C12: =B12-D12 | D12: =E11*$B$4/12 | E12: =E11-C12
A13: 5 | B13: =$B$6 | C13: =B13-D13 | D13: =E12*$B$4/12 | E13: =E12-C13
A14: 6 | B14: =$B$6 | C14: =B14-D14 | D14: =E13*$B$4/12 | E14: =E13-C14
A15: 7 | B15: =$B$6 | C15: =B15-D15 | D15: =E14*$B$4/12 | E15: =E14-C15
A16: 8 | B16: =$B$6 | C16: =B16-D16 | D16: =E15*$B$4/12 | E16: =E15-C16
A17: 9 | B17: =$B$6 | C17: =B17-D17 | D17: =E16*$B$4/12 | E17: =E16-C17
A18: 10 | B18: =$B$6 | C18: =B18-D18 | D18: =E17*$B$4/12 | E18: =E17-C18
A19: 11 | B19: =$B$6 | C19: =B19-D19 | D19: =E18*$B$4/12 | E19: =E18-C19
A20: 12 | B20: =$B$6 | C20: =B20-D20 | D20: =E19*$B$4/12 | E20: =E19-C20
A21: 13 | B21: =$B$6 | C21: =B21-D21 | D21: =E20*$B$4/12 | E21: =E20-C21
... A368: 360 | B368: =$B$6 | C368: =B368-D368 | D368: =E367*$B$4/12 | E368: =E367-C368

Sheet Amort - Refi 3
A1: AMORT - REFI 3
A2: Blank until Refi 3 activated.
A3: Loan Amount | B3: =Assumptions!C125
A4: Annual Rate | B4: =Assumptions!C126
A5: Amort (Years) | B5: =Assumptions!C127
A6: Monthly Payment | B6: =IF(B5>0,PMT(B4/12,B5*12,-B3),0)
A8: Month | B8: Payment | C8: Principal | D8: Interest | E8: Balance
A9: 1 | B9: =$B$6 | C9: =B9-D9 | D9: =$B$3*$B$4/12 | E9: =$B$3-C9
A10: 2 | B10: =$B$6 | C10: =B10-D10 | D10: =E9*$B$4/12 | E10: =E9-C10
A11: 3 | B11: =$B$6 | C11: =B11-D11 | D11: =E10*$B$4/12 | E11: =E10-C11
A12: 4 | B12: =$B$6 | C12: =B12-D12 | D12: =E11*$B$4/12 | E12: =E11-C12
A13: 5 | B13: =$B$6 | C13: =B13-D13 | D13: =E12*$B$4/12 | E13: =E12-C13
A14: 6 | B14: =$B$6 | C14: =B14-D14 | D14: =E13*$B$4/12 | E14: =E13-C14
A15: 7 | B15: =$B$6 | C15: =B15-D15 | D15: =E14*$B$4/12 | E15: =E14-C15
A16: 8 | B16: =$B$6 | C16: =B16-D16 | D16: =E15*$B$4/12 | E16: =E15-C16
A17: 9 | B17: =$B$6 | C17: =B17-D17 | D17: =E16*$B$4/12 | E17: =E16-C17
A18: 10 | B18: =$B$6 | C18: =B18-D18 | D18: =E17*$B$4/12 | E18: =E17-C18
A19: 11 | B19: =$B$6 | C19: =B19-D19 | D19: =E18*$B$4/12 | E19: =E18-C19
A20: 12 | B20: =$B$6 | C20: =B20-D20 | D20: =E19*$B$4/12 | E20: =E19-C20
A21: 13 | B21: =$B$6 | C21: =B21-D21 | D21: =E20*$B$4/12 | E21: =E20-C21
... A368: 360 | B368: =$B$6 | C368: =B368-D368 | D368: =E367*$B$4/12 | E368: =E367-C368

Sheet Exit
A1: EXIT / DISPOSITION
A3: Disposition Calculation
A4: Hold Period | B4: =Assumptions!C14
A5: Exit Year NOI | B5: ='Pro Forma'!K49
A6: Exit Cap Rate | B6: =Assumptions!C193
A7: Gross Sale Price | B7: =IF(B6>0,B5/B6,0)
A8: Disposition Costs (%) | B8: =Assumptions!C194
A9: Disposition Costs ($) | B9: =B7*B8
A10: Net Sale Price | B10: =B7-B9
A12: Loan Payoff
A13: Outstanding Loan Balance | B13: =IF(Assumptions!C121=1,'Amort - Refi 3'!E128,IF(Assumptions!C108=1,'Amort - Refi 2'!E128,IF(Assumptions!C95=1,'Amort - Refi 1'!E128,'Amort - Initial'!E128)))
A14: Net Proceeds After Payoff | B14: =B10-B13
A16: Return Summary
A17: Total Equity | B17: =Assumptions!C91
A18: Total Operating CF | B18: =SUM('Pro Forma'!B63:K62)
A19: Total Refi Proceeds | B19: ='Refi Analysis'!B22+'Refi Analysis'!C22+'Refi Analysis'!D22
A20: Net Exit Proceeds | B20: =B14
A21: Total Return ($) | B21: =B18+B19+B20
A23: EQUITY MULTIPLE | B23: =IF(B17>0,B21/B17,0)

Sheet Cash Waterfall
B1: CASH WATERFALL
B2: All inputs from Assumptions tab. Distributes at every capital event.
B4: PARTNERSHIP STRUCTURE | F4: Year 0 | G4: 1 | H4: 2 | I4: 3 | J4: 4 | K4: 5 | L4: 6 | M4: 7 | N4: 8 | O4: 9 | P4: 10
B6: Equity Contributions | C6: % | D6: Amount
B7: General Partner (GP) | C7: =Assumptions!$C$197 | D7: =C7*D9
B8: Limited Partner (LP) | C8: =Assumptions!$C$198 | D8: =C8*D9
B9: Total Equity | D9: =Assumptions!$C$91
B11: Preferred Return | C11: =Assumptions!$C$204
B13: Waterfall Tiers | D13: IRR Hurdle | E13: GP Promote | F13: LP % | G13: GP %
B14: Tier 1: Pref Return + Return of Capital | D14: =Assumptions!$C$204 | E14: 0% | F14: 100% | G14: 0%
B15: Tier 2 | D15: =Assumptions!$C$205 | E15: =1-Assumptions!$C$206 | F15: =Assumptions!$C$206 | G15: =1-Assumptions!$C$206
B16: Tier 3 | D16: =Assumptions!$C$207 | E16: =1-Assumptions!$C$208 | F16: =Assumptions!$C$208 | G16: =1-Assumptions!$C$208
B17: Tier 4 | D17: =Assumptions!$C$209 | E17: =1-Assumptions!$C$210 | F17: =Assumptions!$C$210 | G17: =1-Assumptions!$C$210
B18: Tier 5 | D18: =Assumptions!$C$211 | E18: =1-Assumptions!$C$212 | F18: =Assumptions!$C$212 | G18: =1-Assumptions!$C$212
B19: Tier 6 (above Tier 5) | E19: =1-Assumptions!$C$213 | F19: =Assumptions!$C$213 | G19: =1-Assumptions!$C$213
B21: PROPERTY-LEVEL CASH FLOWS | F21: Year 0 | G21: 1 | H21: 2 | I21: 3 | J21: 4 | K21: 5 | L21: 6 | M21: 7 | N21: 8 | O21: 9 | P21: 10
B23: Net Property-Level Cash Flow | F23: =-D9 | G23: ='Pro Forma'!B63 | H23: ='Pro Forma'!C63 | I23: ='Pro Forma'!D63 | J23: ='Pro Forma'!E63 | K23: ='Pro Forma'!F63 | L23: ='Pro Forma'!G63 | M23: ='Pro Forma'!H63 | N23: ='Pro Forma'!I63 | O23: ='Pro Forma'!J63 | P23: ='Pro Forma'!K63+Exit!B14
B24: Refi 1 Proceeds | F24: =IF(AND(Assumptions!$C$95=1,0=Assumptions!$C$96),'Refi Analysis'!B22,0) | G24: =IF(AND(Assumptions!$C$95=1,1=Assumptions!$C$96),'Refi Analysis'!B22,0) | H24: =IF(AND(Assumptions!$C$95=1,2=Assumptions!$C$96),'Refi Analysis'!B22,0) | I24: =IF(AND(Assumptions!$C$95=1,3=Assumptions!$C$96),'Refi Analysis'!B22,0) | J24: =IF(AND(Assumptions!$C$95=1,4=Assumptions!$C$96),'Refi Analysis'!B22,0) | K24: =IF(AND(Assumptions!$C$95=1,5=Assumptions!$C$96),'Refi Analysis'!B22,0) | L24: =IF(AND(Assumptions!$C$95=1,6=Assumptions!$C$96),'Refi Analysis'!B22,0) | M24: =IF(AND(Assumptions!$C$95=1,7=Assumptions!$C$96),'Refi Analysis'!B22,0) | N24: =IF(AND(Assumptions!$C$95=1,8=Assumptions!$C$96),'Refi Analysis'!B22,0) | O24: =IF(AND(Assumptions!$C$95=1,9=Assumptions!$C$96),'Refi Analysis'!B22,0) | P24: =IF(AND(Assumptions!$C$95=1,10=Assumptions!$C$96),'Refi Analysis'!B22,0)
B25: Refi 2 Proceeds | F25: =IF(AND(Assumptions!$C$108=1,0=Assumptions!$C$109),'Refi Analysis'!C22,0) | G25: =IF(AND(Assumptions!$C$108=1,1=Assumptions!$C$109),'Refi Analysis'!C22,0) | H25: =IF(AND(Assumptions!$C$108=1,2=Assumptions!$C$109),'Refi Analysis'!C22,0) | I25: =IF(AND(Assumptions!$C$108=1,3=Assumptions!$C$109),'Refi Analysis'!C22,0) | J25: =IF(AND(Assumptions!$C$108=1,4=Assumptions!$C$109),'Refi Analysis'!C22,0) | K25: =IF(AND(Assumptions!$C$108=1,5=Assumptions!$C$109),'Refi Analysis'!C22,0) | L25: =IF(AND(Assumptions!$C$108=1,6=Assumptions!$C$109),'Refi Analysis'!C22,0) | M25: =IF(AND(Assumptions!$C$108=1,7=Assumptions!$C$109),'Refi Analysis'!C22,0) | N25: =IF(AND(Assumptions!$C$108=1,8=Assumptions!$C$109),'Refi Analysis'!C22,0) | O25: =IF(AND(Assumptions!$C$108=1,9=Assumptions!$C$109),'Refi Analysis'!C22,0) | P25: =IF(AND(Assumptions!$C$108=1,10=Assumptions!$C$109),'Refi Analysis'!C22,0)
B26: Refi 3 Proceeds | F26: =IF(AND(Assumptions!$C$121=1,0=Assumptions!$C$122),'Refi Analysis'!D22,0) | G26: =IF(AND(Assumptions!$C$121=1,1=Assumptions!$C$122),'Refi Analysis'!D22,0) | H26: =IF(AND(Assumptions!$C$121=1,2=Assumptions!$C$122),'Refi Analysis'!D22,0) | I26: =IF(AND(Assumptions!$C$121=1,3=Assumptions!$C$122),'Refi Analysis'!D22,0) | J26: =IF(AND(Assumptions!$C$121=1,4=Assumptions!$C$122),'Refi Analysis'!D22,0) | K26: =IF(AND(Assumptions!$C$121=1,5=Assumptions!$C$122),'Refi Analysis'!D22,0) | L26: =IF(AND(Assumptions!$C$121=1,6=Assumptions!$C$122),'Refi Analysis'!D22,0) | M26: =IF(AND(Assumptions!$C$121=1,7=Assumptions!$C$122),'Refi Analysis'!D22,0) | N26: =IF(AND(Assumptions!$C$121=1,8=Assumptions!$C$122),'Refi Analysis'!D22,0) | O26: =IF(AND(Assumptions!$C$121=1,9=Assumptions!$C$122),'Refi Analysis'!D22,0) | P26: =IF(AND(Assumptions!$C$121=1,10=Assumptions!$C$122),'Refi Analysis'!D22,0)
B28: Total Distributable Cash Flow | F28: =F23+F24+F25+F26 | G28: =G23+G24+G25+G26 | H28: =H23+H24+H25+H26 | I28: =I23+I24+I25+I26 | J28: =J23+J24+J25+J26 | K28: =K23+K24+K25+K26 | L28: =L23+L24+L25+L26 | M28: =M23+M24+M25+M26 | ... P28: =P23+P24+P25+P26
B30: PROJECT IRR | D30: =IFERROR(IRR(F28:P28),"N/A")
B31: PROJECT EQUITY MULTIPLE | D31: =IFERROR(SUMIF(F28:P28,">0")/-SUMIF(F28:P28,"<0"),"N/A")
B33: LP / GP RETURN SUMMARY | F33: Year 0 | G33: 1 | H33: 2 | I33: 3 | J33: 4 | K33: 5 | L33: 6 | M33: 7 | N33: 8 | O33: 9 | P33: 10
B35: LIMITED PARTNER (LP) RETURNS | C35: Check
B36: LP Equity Invested | D36: =D8 | F36: =D8 | G36: 0 | H36: 0 | I36: 0 | J36: 0 | K36: 0 | L36: 0 | M36: 0 | N36: 0 | O36: 0 | P36: 0
B37: LP Share of Distributable CF | F37: =F28*$C$8 | G37: =G28*$C$8 | H37: =H28*$C$8 | I37: =I28*$C$8 | J37: =J28*$C$8 | K37: =K28*$C$8 | L37: =L28*$C$8 | M37: =M28*$C$8 | ... P37: =P28*$C$8
B38: Total LP Distributions | C38: =IFERROR(IF(SUM(F37:P37)<=0,"N/A",IF(ROUND(D38,0)=ROUND(SUM(F37:P37),0),"OK","ERROR")),"N/A") | D38: =SUM(F38:P38) | F38: =F74+F87+F101+F115+F122 | G38: =G74+G87+G101+G115+G122 | H38: =H74+H87+H101+H115+H122 | I38: =I74+I87+I101+I115+I122 | J38: =J74+J87+J101+J115+J122 | K38: =K74+K87+K101+K115+K122 | L38: =L74+L87+L101+L115+L122 | M38: =M74+M87+M101+M115+M122 | ... P38: =P74+P87+P101+P115+P122
B39: LP Profit | D39: =D38-D36
B41: LP IRR | D41: =IFERROR(IRR(F41:P41),"N/A") | F41: =-F36+F38 | G41: =-G36+G38 | H41: =-H36+H38 | I41: =-I36+I38 | J41: =-J36+J38 | K41: =-K36+K38 | L41: =-L36+L38 | M41: =-M36+M38 | ... P41: =-P36+P38
B42: LP EQUITY MULTIPLE | D42: =IFERROR(D38/D36,"N/A")
B44: GENERAL PARTNER (GP) RETURNS
B45: GP Equity Invested | D45: =D7 | F45: =D7 | G45: 0 | H45: 0 | I45: 0 | J45: 0 | K45: 0 | L45: 0 | M45: 0 | N45: 0 | O45: 0 | P45: 0
B46: Total GP Distributions | D46: =SUM(F46:P46) | F46: =F75+F88+F102+F116+F123 | G46: =G75+G88+G102+G116+G123 | H46: =H75+H88+H102+H116+H123 | I46: =I75+I88+I102+I116+I123 | J46: =J75+J88+J102+J116+J123 | K46: =K75+K88+K102+K116+K123 | L46: =L75+L88+L102+L116+L123 | M46: =M75+M88+M102+M116+M123 | ... P46: =P75+P88+P102+P116+P123
B47: GP Profit | D47: =D46-D45
B49: GP IRR | D49: =IFERROR(IRR(F49:P49),"N/A") | F49: =-F45+F46 | G49: =-G45+G46 | H49: =-H45+H46 | I49: =-I45+I46 | J49: =-J45+J46 | K49: =-K45+K46 | L49: =-L45+L46 | M49: =-M45+M46 | ... P49: =-P45+P46
B50: GP EQUITY MULTIPLE | D50: =IFERROR(D46/D45,"N/A")
B53: IRR EQUITY WATERFALL — TIER-BY-TIER DETAIL | F53: Year 0 | G53: 1 | H53: 2 | I53: 3 | J53: 4 | K53: 5 | L53: 6 | M53: 7 | N53: 8 | O53: 9 | P53: 10
B55: TIER 1 — Preferred Return + Return of Capital
B56: Hurdle: Up to | C56: =Assumptions!$C$204
B58: LP Beginning Balance | F58: 0 | G58: =F63 | H58: =G63 | I58: =H63 | J58: =I63 | K58: =J63 | L58: =K63 | M58: =L63 | N58: =M63 | ... P58: =O63
B59: LP Preferred Return Accrual | F59: =F58*$C$56 | G59: =G58*$C$56 | H59: =H58*$C$56 | I59: =I58*$C$56 | J59: =J58*$C$56 | K59: =K58*$C$56 | L59: =L58*$C$56 | M59: =M58*$C$56 | ... P59: =P58*$C$56
B60: LP Contributions | F60: =$D$8 | G60: 0 | H60: 0 | I60: 0 | J60: 0 | K60: 0 | L60: 0 | M60: 0 | N60: 0 | O60: 0 | P60: 0
B61: LP Available Cash (LP share) | F61: =MAX(F28,0)*$C$8 | G61: =MAX(G28,0)*$C$8 | H61: =MAX(H28,0)*$C$8 | I61: =MAX(I28,0)*$C$8 | J61: =MAX(J28,0)*$C$8 | K61: =MAX(K28,0)*$C$8 | L61: =MAX(L28,0)*$C$8 | M61: =MAX(M28,0)*$C$8 | ... P61: =MAX(P28,0)*$C$8
B62: LP Distribution (Tier 1) | F62: 0 | G62: =MIN(G58+G59,G61) | H62: =MIN(H58+H59,H61) | I62: =MIN(I58+I59,I61) | J62: =MIN(J58+J59,J61) | K62: =MIN(K58+K59,K61) | L62: =MIN(L58+L59,L61) | M62: =MIN(M58+M59,M61) | N62: =MIN(N58+N59,N61) | ... P62: =MIN(P58+P59,P61)
B63: LP Ending Balance | F63: =F58+F59+F60-F62 | G63: =G58+G59+G60-G62 | H63: =H58+H59+H60-H62 | I63: =I58+I59+I60-I62 | J63: =J58+J59+J60-J62 | K63: =K58+K59+K60-K62 | L63: =L58+L59+L60-L62 | M63: =M58+M59+M60-M62 | ... P63: =P58+P59+P60-P62
B64: LP IRR Check (Tier 1) | E64: =IFERROR(IRR(F64:P64),"N/A") | F64: =-F60+F62 | G64: =-G60+G62 | H64: =-H60+H62 | I64: =-I60+I62 | J64: =-J60+J62 | K64: =-K60+K62 | L64: =-L60+L62 | M64: =-M60+M62 | ... P64: =-P60+P62
B66: GP Beginning Balance | F66: 0 | G66: =F71 | H66: =G71 | I66: =H71 | J66: =I71 | K66: =J71 | L66: =K71 | M66: =L71 | N66: =M71 | ... P66: =O71
B67: GP Preferred Return Accrual | F67: =F66*$C$56 | G67: =G66*$C$56 | H67: =H66*$C$56 | I67: =I66*$C$56 | J67: =J66*$C$56 | K67: =K66*$C$56 | L67: =L66*$C$56 | M67: =M66*$C$56 | ... P67: =P66*$C$56
B68: GP Contributions | F68: =$D$7 | G68: 0 | H68: 0 | I68: 0 | J68: 0 | K68: 0 | L68: 0 | M68: 0 | N68: 0 | O68: 0 | P68: 0
B69: GP Available Cash (GP share) | F69: =MAX(F28,0)*$C$7 | G69: =MAX(G28,0)*$C$7 | H69: =MAX(H28,0)*$C$7 | I69: =MAX(I28,0)*$C$7 | J69: =MAX(J28,0)*$C$7 | K69: =MAX(K28,0)*$C$7 | L69: =MAX(L28,0)*$C$7 | M69: =MAX(M28,0)*$C$7 | ... P69: =MAX(P28,0)*$C$7
B70: GP Distribution (Tier 1) | F70: 0 | G70: =MIN(G66+G67,G69) | H70: =MIN(H66+H67,H69) | I70: =MIN(I66+I67,I69) | J70: =MIN(J66+J67,J69) | K70: =MIN(K66+K67,K69) | L70: =MIN(L66+L67,L69) | M70: =MIN(M66+M67,M69) | N70: =MIN(N66+N67,N69) | ... P70: =MIN(P66+P67,P69)
B71: GP Ending Balance | F71: =F66+F67+F68-F70 | G71: =G66+G67+G68-G70 | H71: =H66+H67+H68-H70 | I71: =I66+I67+I68-I70 | J71: =J66+J67+J68-J70 | K71: =K66+K67+K68-K70 | L71: =L66+L67+L68-L70 | M71: =M66+M67+M68-M70 | ... P71: =P66+P67+P68-P70
B73: Total Tier 1 Distributions (LP+GP) | F73: =F62+F70 | G73: =G62+G70 | H73: =H62+H70 | I73: =I62+I70 | J73: =J62+J70 | K73: =K62+K70 | L73: =L62+L70 | M73: =M62+M70 | ... P73: =P62+P70
B74: LP Distribution (Tier 1) | F74: =F62 | G74: =G62 | H74: =H62 | I74: =I62 | J74: =J62 | K74: =K62 | L74: =L62 | M74: =M62 | ... P74: =P62
B75: GP Distribution (Tier 1) | F75: =F70 | G75: =G70 | H75: =H70 | I75: =I70 | J75: =J70 | K75: =K70 | L75: =L70 | M75: =M70 | ... P75: =P70
B76: Cash Flow Remaining After Tier 1 | F76: =MAX(F28-F73,0) | G76: =MAX(G28-G73,0) | H76: =MAX(H28-H73,0) | I76: =MAX(I28-I73,0) | J76: =MAX(J28-J73,0) | K76: =MAX(K28-K73,0) | L76: =MAX(L28-L73,0) | M76: =MAX(M28-M73,0) | ... P76: =MAX(P28-P73,0)
B78: TIER 2 — Promote
B79: Hurdle: Up to | C79: =Assumptions!$C$205
B80: LP / GP Split | C80: =Assumptions!$C$206 | D80: =1-C80
B82: LP Beginning Balance | F82: 0 | G82: =F86 | H82: =G86 | I82: =H86 | J82: =I86 | K82: =J86 | L82: =K86 | M82: =L86 | N82: =M86 | ... P82: =O86
B83: Req'd Return to hit Hurdle 2 | F83: =F82*$C$79 | G83: =G82*$C$79 | H83: =H82*$C$79 | I83: =I82*$C$79 | J83: =J82*$C$79 | K83: =K82*$C$79 | L83: =L82*$C$79 | M83: =M82*$C$79 | ... P83: =P82*$C$79
B84: Prior LP Distributions | F84: =F74 | G84: =G74 | H84: =H74 | I84: =I74 | J84: =J74 | K84: =K74 | L84: =L74 | M84: =M74 | ... P84: =P74
B85: LP Distribution (Tier 2) | F85: 0 | G85: =MAX(MIN(G82+G83-G84,G76*$C$80),0) | H85: =MAX(MIN(H82+H83-H84,H76*$C$80),0) | I85: =MAX(MIN(I82+I83-I84,I76*$C$80),0) | J85: =MAX(MIN(J82+J83-J84,J76*$C$80),0) | K85: =MAX(MIN(K82+K83-K84,K76*$C$80),0) | L85: =MAX(MIN(L82+L83-L84,L76*$C$80),0) | M85: =MAX(MIN(M82+M83-M84,M76*$C$80),0) | N85: =MAX(MIN(N82+N83-N84,N76*$C$80),0) | ... P85: =MAX(MIN(P82+P83-P84,P76*$C$80),0)
B86: LP Ending Balance | F86: =$D$8 | G86: =G82+G83+0-G84-G85 | H86: =H82+H83+0-H84-H85 | I86: =I82+I83+0-I84-I85 | J86: =J82+J83+0-J84-J85 | K86: =K82+K83+0-K84-K85 | L86: =L82+L83+0-L84-L85 | M86: =M82+M83+0-M84-M85 | N86: =N82+N83+0-N84-N85 | ... P86: =P82+P83+0-P84-P85
B87: LP Distribution (Tier 2) | F87: =F85 | G87: =G85 | H87: =H85 | I87: =I85 | J87: =J85 | K87: =K85 | L87: =L85 | M87: =M85 | ... P87: =P85
B88: GP Distribution (Tier 2) | F88: =IF($C$80>0,F87/$C$80*$D$80,0) | G88: =IF($C$80>0,G87/$C$80*$D$80,0) | H88: =IF($C$80>0,H87/$C$80*$D$80,0) | I88: =IF($C$80>0,I87/$C$80*$D$80,0) | J88: =IF($C$80>0,J87/$C$80*$D$80,0) | K88: =IF($C$80>0,K87/$C$80*$D$80,0) | L88: =IF($C$80>0,L87/$C$80*$D$80,0) | M88: =IF($C$80>0,M87/$C$80*$D$80,0) | ... P88: =IF($C$80>0,P87/$C$80*$D$80,0)
B89: Total Tier 2 Distributions | F89: =F87+F88 | G89: =G87+G88 | H89: =H87+H88 | I89: =I87+I88 | J89: =J87+J88 | K89: =K87+K88 | L89: =L87+L88 | M89: =M87+M88 | ... P89: =P87+P88
B90: Cash Flow Remaining After Tier 2 | F90: =MAX(F76-F89,0) | G90: =MAX(G76-G89,0) | H90: =MAX(H76-H89,0) | I90: =MAX(I76-I89,0) | J90: =MAX(J76-J89,0) | K90: =MAX(K76-K89,0) | L90: =MAX(L76-L89,0) | M90: =MAX(M76-M89,0) | ... P90: =MAX(P76-P89,0)
B92: TIER 3 — Promote
B93: Hurdle: Up to | C93: =Assumptions!$C$207
B94: LP / GP Split | C94: =Assumptions!$C$208 | D94: =1-C94
B96: LP Beginning Balance | F96: 0 | G96: =F100 | H96: =G100 | I96: =H100 | J96: =I100 | K96: =J100 | L96: =K100 | M96: =L100 | N96: =M100 | ... P96: =O100
B97: Req'd Return to hit Hurdle 3 | F97: =F96*$C$93 | G97: =G96*$C$93 | H97: =H96*$C$93 | I97: =I96*$C$93 | J97: =J96*$C$93 | K97: =K96*$C$93 | L97: =L96*$C$93 | M97: =M96*$C$93 | ... P97: =P96*$C$93
B98: Prior LP Distributions | F98: =F74+F87 | G98: =G74+G87 | H98: =H74+H87 | I98: =I74+I87 | J98: =J74+J87 | K98: =K74+K87 | L98: =L74+L87 | M98: =M74+M87 | ... P98: =P74+P87
B99: LP Distribution (Tier 3) | F99: 0 | G99: =MAX(MIN(G96+G97-G98,G90*$C$94),0) | H99: =MAX(MIN(H96+H97-H98,H90*$C$94),0) | I99: =MAX(MIN(I96+I97-I98,I90*$C$94),0) | J99: =MAX(MIN(J96+J97-J98,J90*$C$94),0) | K99: =MAX(MIN(K96+K97-K98,K90*$C$94),0) | L99: =MAX(MIN(L96+L97-L98,L90*$C$94),0) | M99: =MAX(MIN(M96+M97-M98,M90*$C$94),0) | N99: =MAX(MIN(N96+N97-N98,N90*$C$94),0) | ... P99: =MAX(MIN(P96+P97-P98,P90*$C$94),0)
B100: LP Ending Balance | F100: =$D$8 | G100: =G96+G97-G98-G99 | H100: =H96+H97-H98-H99 | I100: =I96+I97-I98-I99 | J100: =J96+J97-J98-J99 | K100: =K96+K97-K98-K99 | L100: =L96+L97-L98-L99 | M100: =M96+M97-M98-M99 | N100: =N96+N97-N98-N99 | ... P100: =P96+P97-P98-P99
B101: LP Distribution (Tier 3) | F101: =F99 | G101: =G99 | H101: =H99 | I101: =I99 | J101: =J99 | K101: =K99 | L101: =L99 | M101: =M99 | ... P101: =P99
B102: GP Distribution (Tier 3) | F102: =IF($C$94>0,F101/$C$94*$D$94,0) | G102: =IF($C$94>0,G101/$C$94*$D$94,0) | H102: =IF($C$94>0,H101/$C$94*$D$94,0) | I102: =IF($C$94>0,I101/$C$94*$D$94,0) | J102: =IF($C$94>0,J101/$C$94*$D$94,0) | K102: =IF($C$94>0,K101/$C$94*$D$94,0) | L102: =IF($C$94>0,L101/$C$94*$D$94,0) | M102: =IF($C$94>0,M101/$C$94*$D$94,0) | ... P102: =IF($C$94>0,P101/$C$94*$D$94,0)
B103: Total Tier 3 Distributions | F103: =F101+F102 | G103: =G101+G102 | H103: =H101+H102 | I103: =I101+I102 | J103: =J101+J102 | K103: =K101+K102 | L103: =L101+L102 | M103: =M101+M102 | ... P103: =P101+P102
B104: Cash Flow Remaining After Tier 3 | F104: =MAX(F90-F103,0) | G104: =MAX(G90-G103,0) | H104: =MAX(H90-H103,0) | I104: =MAX(I90-I103,0) | J104: =MAX(J90-J103,0) | K104: =MAX(K90-K103,0) | L104: =MAX(L90-L103,0) | M104: =MAX(M90-M103,0) | ... P104: =MAX(P90-P103,0)
B106: TIER 4 — Promote
B107: Hurdle: Up to | C107: =Assumptions!$C$209
B108: LP / GP Split | C108: =Assumptions!$C$210 | D108: =1-C108
B110: LP Beginning Balance | F110: 0 | G110: =F114 | H110: =G114 | I110: =H114 | J110: =I114 | K110: =J114 | L110: =K114 | M110: =L114 | N110: =M114 | ... P110: =O114
B111: Req'd Return to hit Hurdle 4 | F111: =F110*$C$107 | G111: =G110*$C$107 | H111: =H110*$C$107 | I111: =I110*$C$107 | J111: =J110*$C$107 | K111: =K110*$C$107 | L111: =L110*$C$107 | M111: =M110*$C$107 | ... P111: =P110*$C$107
B112: Prior LP Distributions | F112: =F74+F87+F101 | G112: =G74+G87+G101 | H112: =H74+H87+H101 | I112: =I74+I87+I101 | J112: =J74+J87+J101 | K112: =K74+K87+K101 | L112: =L74+L87+L101 | M112: =M74+M87+M101 | ... P112: =P74+P87+P101
B113: LP Distribution (Tier 4) | F113: 0 | G113: =MAX(MIN(G110+G111-G112,G104*$C$108),0) | H113: =MAX(MIN(H110+H111-H112,H104*$C$108),0) | I113: =MAX(MIN(I110+I111-I112,I104*$C$108),0) | J113: =MAX(MIN(J110+J111-J112,J104*$C$108),0) | K113: =MAX(MIN(K110+K111-K112,K104*$C$108),0) | L113: =MAX(MIN(L110+L111-L112,L104*$C$108),0) | M113: =MAX(MIN(M110+M111-M112,M104*$C$108),0) | N113: =MAX(MIN(N110+N111-N112,N104*$C$108),0) | ... P113: =MAX(MIN(P110+P111-P112,P104*$C$108),0)
B114: LP Ending Balance | F114: =$D$8 | G114: =G110+G111-G112-G113 | H114: =H110+H111-H112-H113 | I114: =I110+I111-I112-I113 | J114: =J110+J111-J112-J113 | K114: =K110+K111-K112-K113 | L114: =L110+L111-L112-L113 | M114: =M110+M111-M112-M113 | N114: =N110+N111-N112-N113 | ... P114: =P110+P111-P112-P113
B115: LP Distribution (Tier 4) | F115: =F113 | G115: =G113 | H115: =H113 | I115: =I113 | J115: =J113 | K115: =K113 | L115: =L113 | M115: =M113 | ... P115: =P113
B116: GP Distribution (Tier 4) | F116: =IF($C$108>0,F115/$C$108*$D$108,0) | G116: =IF($C$108>0,G115/$C$108*$D$108,0) | H116: =IF($C$108>0,H115/$C$108*$D$108,0) | I116: =IF($C$108>0,I115/$C$108*$D$108,0) | J116: =IF($C$108>0,J115/$C$108*$D$108,0) | K116: =IF($C$108>0,K115/$C$108*$D$108,0) | L116: =IF($C$108>0,L115/$C$108*$D$108,0) | M116: =IF($C$108>0,M115/$C$108*$D$108,0) | ... P116: =IF($C$108>0,P115/$C$108*$D$108,0)
B117: Total Tier 4 Distributions | F117: =F115+F116 | G117: =G115+G116 | H117: =H115+H116 | I117: =I115+I116 | J117: =J115+J116 | K117: =K115+K116 | L117: =L115+L116 | M117: =M115+M116 | ... P117: =P115+P116
B118: Cash Flow Remaining After Tier 4 | F118: =MAX(F104-F117,0) | G118: =MAX(G104-G117,0) | H118: =MAX(H104-H117,0) | I118: =MAX(I104-I117,0) | J118: =MAX(J104-J117,0) | K118: =MAX(K104-K117,0) | L118: =MAX(L104-L117,0) | M118: =MAX(M104-M117,0) | ... P118: =MAX(P104-P117,0)
B120: TIER 5 — Above Hurdle 4 (Super Promote)
B121: LP / GP Split | C121: =Assumptions!$C$212 | D121: =1-C121
B122: LP Distribution (Tier 5) | F122: =F118*$C$121 | G122: =G118*$C$121 | H122: =H118*$C$121 | I122: =I118*$C$121 | J122: =J118*$C$121 | K122: =K118*$C$121 | L122: =L118*$C$121 | M122: =M118*$C$121 | ... P122: =P118*$C$121
B123: GP Distribution (Tier 5) | F123: =F118-F122 | G123: =G118-G122 | H123: =H118-H122 | I123: =I118-I122 | J123: =J118-J122 | K123: =K118-K122 | L123: =L118-L122 | M123: =M118-M122 | ... P123: =P118-P122
B124: Total Tier 5 Distributions | F124: =F122+F123 | G124: =G122+G123 | H124: =H122+H123 | I124: =I122+I123 | J124: =J122+J123 | K124: =K122+K123 | L124: =L122+L123 | M124: =M122+M123 | ... P124: =P122+P123
B125: Cash Flow Remaining (should be 0) | F125: =F118-F124 | G125: =G118-G124 | H125: =H118-H124 | I125: =I118-I124 | J125: =J118-J124 | K125: =K118-K124 | L125: =L118-L124 | M125: =M118-M124 | ... P125: =P118-P124
B127: VERIFICATION & ERROR CHECKS | F127: Year 0 | G127: 1 | H127: 2 | I127: 3 | J127: 4 | K127: 5 | L127: 6 | M127: 7 | N127: 8 | O127: 9 | P127: 10
...

Sheet Returns Summary
A1: RETURNS SUMMARY
A2: All values reference other tabs. No hardcoded numbers.
A4: Investment Overview
A5: Property | B5: =Assumptions!C5
A6: Purchase Price | B6: =Assumptions!C17
A7: Total Project Cost | B7: =Assumptions!C89
A8: Total Equity | B8: =Assumptions!C91
A9: Hold Period | B9: =Assumptions!C14
A11: Return Metrics
A12: Year 1 NOI | B12: ='Pro Forma'!B49
A13: Going-In Cap Rate | B13: =IF(Assumptions!C17>0,B12/Assumptions!C17,0)
A14: Year 1 Cash-on-Cash | B14: =IF(Assumptions!C91>0,'Pro Forma'!B63/Assumptions!C91,0)
A15: Year 1 DSCR | B15: ='Pro Forma'!B61
A16: Exit Cap Rate | B16: =Assumptions!C193
A17: Gross Sale Price | B17: =Exit!B7
A19: Equity Multiple & Distributions
A20: Total Operating CF | B20: =SUM('Pro Forma'!B63:K63)
A21: Total Refi Proceeds | B21: ='Refi Analysis'!B22+'Refi Analysis'!C22+'Refi Analysis'!D22
A22: Net Exit Proceeds | B22: =Exit!B14
A23: Total Distributions | B23: =B20+B21+B22
A25: EQUITY MULTIPLE | B25: =IF(Assumptions!C91>0,B23/Assumptions!C91,0)
A27: LP IRR (from Waterfall) | B27: ='Cash Waterfall'!D41
A28: LP Equity Multiple | B28: ='Cash Waterfall'!D42
A29: GP IRR | B29: ='Cash Waterfall'!D49
A30: GP Equity Multiple | B30: ='Cash Waterfall'!D50
A31: Levered IRR (Property) | B31: ='Cash Waterfall'!D30

Sheet Sensitivity
A1: SENSITIVITY ANALYSIS
A2: How key returns change across different scenarios. Rent Growth (columns) × Exit Cap Rate (rows).
B4: LEVERED IRR | K4: EQUITY MULTIPLE
B5: Project-level IRR under different rent growth and exit cap assumptions | K5: Project-level equity multiple under different scenarios
B6: Exit Cap ↓ Rent Growth → | C6: =Assumptions!$C$222+0*Assumptions!$C$224 | D6: =Assumptions!$C$222+1*Assumptions!$C$224 | E6: =Assumptions!$C$222+2*Assumptions!$C$224 | F6: =Assumptions!$C$222+3*Assumptions!$C$224 | G6: =Assumptions!$C$222+4*Assumptions!$C$224 | H6: =Assumptions!$C$222+5*Assumptions!$C$224 | K6: Exit Cap ↓ Rent Growth → | L6: =Assumptions!$C$222+0*Assumptions!$C$224 | M6: =Assumptions!$C$222+1*Assumptions!$C$224 | N6: =Assumptions!$C$222+2*Assumptions!$C$224 | O6: =Assumptions!$C$222+3*Assumptions!$C$224 | P6: =Assumptions!$C$222+4*Assumptions!$C$224 | Q6: =Assumptions!$C$222+5*Assumptions!$C$224
B7: =Assumptions!$C$225+0*Assumptions!$C$227 | C7: — | D7: — | E7: — | F7: — | G7: — | H7: — | K7: =Assumptions!$C$225+0*Assumptions!$C$227 | L7: — | M7: — | N7: — | O7: — | P7: — | Q7: —
B8: =Assumptions!$C$225+1*Assumptions!$C$227 | C8: — | D8: — | E8: — | F8: — | G8: — | H8: — | K8: =Assumptions!$C$225+1*Assumptions!$C$227 | L8: — | M8: — | N8: — | O8: — | P8: — | Q8: —
B9: =Assumptions!$C$225+2*Assumptions!$C$227 | C9: — | D9: — | E9: — | F9: — | G9: — | H9: — | K9: =Assumptions!$C$225+2*Assumptions!$C$227 | L9: — | M9: — | N9: — | O9: — | P9: — | Q9: —
B10: =Assumptions!$C$225+3*Assumptions!$C$227 | C10: — | D10: — | E10: — | F10: — | G10: — | H10: — | K10: =Assumptions!$C$225+3*Assumptions!$C$227 | L10: — | M10: — | N10: — | O10: — | P10: — | Q10: —
B11: =Assumptions!$C$225+4*Assumptions!$C$227 | C11: — | D11: — | E11: — | F11: — | G11: — | H11: — | K11: =Assumptions!$C$225+4*Assumptions!$C$227 | L11: — | M11: — | N11: — | O11: — | P11: — | Q11: —
B12: =Assumptions!$C$225+5*Assumptions!$C$227 | C12: — | D12: — | E12: — | F12: — | G12: — | H12: — | K12: =Assumptions!$C$225+5*Assumptions!$C$227 | L12: — | M12: — | N12: — | O12: — | P12: — | Q12: —
B13: =Assumptions!$C$225+6*Assumptions!$C$227 | C13: — | D13: — | E13: — | F13: — | G13: — | H13: — | K13: =Assumptions!$C$225+6*Assumptions!$C$227 | L13: — | M13: — | N13: — | O13: — | P13: — | Q13: —
B15: Values calculated by Python underwriting script (requires iterative IRR calculation). | K15: Values calculated by Python underwriting script.
A16: OPERATING METRICS SENSITIVITY
B18: YEAR 1 NOI | K18: YEAR 1 CASH-ON-CASH RETURN
B19: Vacancy Rate (columns) × Expense Growth (rows) | K19: Purchase Price (columns) × LTV (rows)
B20: Exp Growth ↓ Vacancy → | C20: 0.05 | D20: 0.075 | E20: 0.1 | F20: 0.125 | G20: 0.15 | H20: 0.2 | K20: LTV ↓ Price → | L20: =Assumptions!$C$17*(1+-0.15) | M20: =Assumptions!$C$17*(1+-0.1) | N20: =Assumptions!$C$17*(1+-0.05) | O20: =Assumptions!$C$17 | P20: =Assumptions!$C$17*(1+0.05) | Q20: =Assumptions!$C$17*(1+0.1)
B21: 0.01 | C21: — | D21: — | E21: — | F21: — | G21: — | H21: — | K21: 0.6 | L21: — | M21: — | N21: — | O21: — | P21: — | Q21: —
B22: 0.02 | C22: — | D22: — | E22: — | F22: — | G22: — | H22: — | K22: 0.65 | L22: — | M22: — | N22: — | O22: — | P22: — | Q22: —
B23: 0.03 | C23: — | D23: — | E23: — | F23: — | G23: — | H23: — | K23: 0.7 | L23: — | M23: — | N23: — | O23: — | P23: — | Q23: —
B24: 0.04 | C24: — | D24: — | E24: — | F24: — | G24: — | H24: — | K24: 0.75 | L24: — | M24: — | N24: — | O24: — | P24: — | Q24: —
B25: 0.05 | C25: — | D25: — | E25: — | F25: — | G25: — | H25: — | K25: 0.8 | L25: — | M25: — | N25: — | O25: — | P25: — | Q25: —
B26: Values calculated by Python underwriting script. | K26: Values calculated by Python underwriting script.
